addon_odoo_wheel/__init__.py
addon_odoo_wheel/__main__.py
addon_odoo_wheel/builder.py
addon_odoo_wheel/compat.py
addon_odoo_wheel/contributors.py
addon_odoo_wheel/contributors_api.py
addon_odoo_wheel/exceptions.py
addon_odoo_wheel/metadata.py
addon_odoo_wheel/utils.py
addon_odoo_wheel/version.py
addon_odoo_wheel-0.4.0.dist-info/METADATA
addon_odoo_wheel-0.4.0.dist-info/WHEEL
addon_odoo_wheel-0.4.0.dist-info/entry_points.txt
addon_odoo_wheel-0.4.0.dist-info/RECORD
