Metadata-Version: 2.4
Name: addon-odoo-wheel
Version: 0.4.0
Summary: Generic and simple build backend for a single Odoo addon
Project-URL: Homepage, https://gitlab.mangono.io/odoo/addon-odoo-wheel
Project-URL: Source, https://gitlab.mangono.io/odoo/addon-odoo-wheel
Project-URL: Tracker, https://gitlab.mangono.io/odoo/addon-odoo-wheel/-/issues
Author-email: Alexis Pasquier <alexis.pasquier@mangono.fr>
License-Expression: MIT
Classifier: Development Status :: 3 - Alpha
Classifier: Framework :: Odoo
Classifier: Programming Language :: Python :: 3.7
Classifier: Programming Language :: Python :: 3.8
Classifier: Programming Language :: Python :: 3.9
Classifier: Programming Language :: Python :: 3.10
Classifier: Programming Language :: Python :: 3.11
Classifier: Programming Language :: Python :: 3.12
Classifier: Programming Language :: Python :: 3.13
Classifier: Topic :: Software Development :: Build Tools
Requires-Python: >=3.8
Requires-Dist: importlib-metadata>=6.8.0
Requires-Dist: manifestoo-core
Requires-Dist: packaging
Requires-Dist: tomli; python_version < '3.11'
Requires-Dist: typing-extensions>=4.7.1
Requires-Dist: wheel
